sortingFunctions/__init__.py
sortingFunctions/app.py
sortingFunctions/bubble.py
sortingFunctions/insertion.py
sortingFunctions/quick.py
sortingFunctions/selection.py
sortingFunctions/text.py
sortingFunctions-0.1.dist-info/METADATA
sortingFunctions-0.1.dist-info/WHEEL
sortingFunctions-0.1.dist-info/top_level.txt
sortingFunctions-0.1.dist-info/RECORD
