Metadata-Version: 2.1
Name: sortingFunctions
Version: 0.1
Summary: sorting n3
Home-page: https://gitlab.propulsion-home.ch/x/conda
Author: oliver hofmann
Author-email: x@pri.la
License: MIT
Platform: UNKNOWN
